{"relationshipsSections":[{"title":"Inherits From","identifiers":["doc:\/\/AtomicXCore\/objc(cs)NSObject"],"type":"inheritsFrom","kind":"relationships"},{"title":"Conforms To","identifiers":["doc:\/\/AtomicXCore\/objc(pl)NSObject","doc:\/\/AtomicXCore\/s7CVarArgP","doc:\/\/AtomicXCore\/s28CustomDebugStringConvertibleP","doc:\/\/AtomicXCore\/s23CustomStringConvertibleP","doc:\/\/AtomicXCore\/SQ","doc:\/\/AtomicXCore\/SH"],"type":"conformsTo","kind":"relationships"}],"sections":[],"primaryContentSections":[{"kind":"declarations","declarations":[{"platforms":["iOS"],"languages":["swift"],"tokens":[{"kind":"keyword","text":"class"},{"kind":"text","text":" "},{"kind":"identifier","text":"CallStore"}]}]},{"content":[{"text":"Overview","level":2,"anchor":"overview","type":"heading"},{"inlineContent":[{"type":"codeVoice","code":"CallStore"},{"type":"text","text":" Manages all audio\/video call related operations,"},{"type":"text","text":" "},{"type":"text","text":"including initiating, answering, rejecting, hanging up, group call management, and call history management."},{"type":"text","text":" "},{"type":"text","text":"Audio\/video call functionality is implemented through "},{"type":"codeVoice","code":"CallStore"},{"type":"text","text":" for real-time audio\/video interaction between users. "},{"type":"codeVoice","code":"CallStore"},{"type":"text","text":" provides a comprehensive set of APIs to manage the entire call lifecycle."}],"type":"paragraph"},{"text":"Key Features","level":3,"anchor":"Key-Features","type":"heading"},{"items":[{"content":[{"inlineContent":[{"type":"strong","inlineContent":[{"text":"Create Audio\/Video Calls","type":"text"}]},{"text":"：Support initiating audio or video calls to one or multiple users, with configurable timeout, custom data, and other parameters","type":"text"}],"type":"paragraph"}]},{"content":[{"type":"paragraph","inlineContent":[{"inlineContent":[{"type":"text","text":"Answer\/Reject Audio\/Video Calls"}],"type":"strong"},{"text":"：When receiving an incoming call invitation, you can choose to answer or reject","type":"text"}]}]},{"content":[{"type":"paragraph","inlineContent":[{"type":"strong","inlineContent":[{"text":"Hang Up Audio\/Video Calls","type":"text"}]},{"type":"text","text":"：End the current ongoing audio\/video call"}]}]},{"content":[{"inlineContent":[{"inlineContent":[{"text":"Group Call Management","type":"text"}],"type":"strong"},{"text":"：Support joining existing group calls or inviting other users to join during a call","type":"text"}],"type":"paragraph"}]},{"content":[{"type":"paragraph","inlineContent":[{"type":"strong","inlineContent":[{"type":"text","text":"Call History Management"}]},{"type":"text","text":"：Query recent call records (with pagination support), delete specified call records"}]}]},{"content":[{"type":"paragraph","inlineContent":[{"type":"strong","inlineContent":[{"type":"text","text":"Event-Driven Architecture"}]},{"type":"text","text":"：Provides event listeners for call started, call received, call ended, etc."}]}]},{"content":[{"type":"paragraph","inlineContent":[{"inlineContent":[{"text":"State Subscription","type":"text"}],"type":"strong"},{"text":"：Real-time subscription to current call state, including participant list, volume information, network quality, etc.","type":"text"}]}]}],"type":"unorderedList"},{"style":"important","name":"Important","content":[{"inlineContent":[{"type":"text","text":"Ensure the SDK is initialized before accessing the "},{"type":"reference","isActive":true,"identifier":"doc:\/\/AtomicXCore\/documentation\/AtomicXCore\/CallStore\/shared"},{"type":"text","text":" singleton. Do not instantiate it directly, as doing so will prevent you from receiving call state updates."}],"type":"paragraph"}],"type":"aside"},{"style":"note","name":"Note","content":[{"type":"paragraph","inlineContent":[{"type":"text","text":"Call state updates are delivered through the "},{"isActive":true,"type":"reference","identifier":"doc:\/\/AtomicXCore\/documentation\/AtomicXCore\/CallStore\/state"},{"type":"text","text":" publisher. Subscribe to it to receive real-time updates of call data."}]}],"type":"aside"},{"text":"Call Operations Overview","level":3,"anchor":"Call-Operations-Overview","type":"heading"},{"inlineContent":[{"text":"The following table shows the main call operations","type":"text"}],"type":"paragraph"},{"header":"row","rows":[[[{"inlineContent":[{"type":"text","text":"Feature"}],"type":"paragraph"}],[{"inlineContent":[{"type":"text","text":"Method"}],"type":"paragraph"}],[{"inlineContent":[{"type":"text","text":"Description"}],"type":"paragraph"}]],[[{"inlineContent":[{"type":"text","text":"Create Call"}],"type":"paragraph"}],[{"inlineContent":[{"type":"codeVoice","code":"calls"}],"type":"paragraph"}],[{"inlineContent":[{"text":"Create an audio or video call to specified users","type":"text"}],"type":"paragraph"}]],[[{"inlineContent":[{"text":"Answer Call","type":"text"}],"type":"paragraph"}],[{"inlineContent":[{"type":"codeVoice","code":"accept"}],"type":"paragraph"}],[{"inlineContent":[{"text":"Answer an incoming call","type":"text"}],"type":"paragraph"}]],[[{"inlineContent":[{"text":"Reject Call","type":"text"}],"type":"paragraph"}],[{"inlineContent":[{"type":"codeVoice","code":"reject"}],"type":"paragraph"}],[{"inlineContent":[{"text":"Reject an incoming call","type":"text"}],"type":"paragraph"}]],[[{"inlineContent":[{"type":"text","text":"Hang Up Call"}],"type":"paragraph"}],[{"inlineContent":[{"type":"codeVoice","code":"hangup"}],"type":"paragraph"}],[{"inlineContent":[{"type":"text","text":"Hang up the current call"}],"type":"paragraph"}]],[[{"inlineContent":[{"text":"Join Call","type":"text"}],"type":"paragraph"}],[{"inlineContent":[{"code":"join","type":"codeVoice"}],"type":"paragraph"}],[{"inlineContent":[{"type":"text","text":"Actively join a group call"}],"type":"paragraph"}]],[[{"inlineContent":[{"type":"text","text":"Invite Users"}],"type":"paragraph"}],[{"inlineContent":[{"type":"codeVoice","code":"invite"}],"type":"paragraph"}],[{"inlineContent":[{"text":"Invite other users to join the current call","type":"text"}],"type":"paragraph"}]]],"type":"table"},{"text":"Call History Management","level":3,"anchor":"Call-History-Management","type":"heading"},{"header":"row","rows":[[[{"inlineContent":[{"type":"text","text":"Feature"}],"type":"paragraph"}],[{"inlineContent":[{"type":"text","text":"Method"}],"type":"paragraph"}],[{"inlineContent":[{"type":"text","text":"Description"}],"type":"paragraph"}]],[[{"inlineContent":[{"type":"text","text":"Query Records"}],"type":"paragraph"}],[{"inlineContent":[{"code":"queryRecentCalls","type":"codeVoice"}],"type":"paragraph"}],[{"inlineContent":[{"text":"Query recent call records (with pagination support)","type":"text"}],"type":"paragraph"}]],[[{"inlineContent":[{"text":"Delete Records","type":"text"}],"type":"paragraph"}],[{"inlineContent":[{"type":"codeVoice","code":"deleteRecentCalls"}],"type":"paragraph"}],[{"inlineContent":[{"text":"Delete specified call records","type":"text"}],"type":"paragraph"}]]],"type":"table"},{"text":"Usage Example","level":3,"anchor":"Usage-Example","type":"heading"},{"code":["import AtomicXCore","","\/\/ Create a video call","CallStore.shared.calls(participantIds: [\"mike\"], callMediaType: .video, params: nil) {","} fail: { code, message in","}"],"syntax":"swift","type":"codeListing"},{"style":"warning","name":"Warning","content":[{"type":"paragraph","inlineContent":[{"text":"Please ensure proper handling of UI state after the call ends to avoid UI anomalies.","type":"text"}]}],"type":"aside"}],"kind":"content"}],"seeAlsoSections":[{"title":"Related Documentation","identifiers":["doc:\/\/AtomicXCore\/documentation\/AtomicXCore\/CallMediaType","doc:\/\/AtomicXCore\/documentation\/AtomicXCore\/CallEndReason","doc:\/\/AtomicXCore\/documentation\/AtomicXCore\/CallDirection","doc:\/\/AtomicXCore\/documentation\/AtomicXCore\/CallParticipantStatus","doc:\/\/AtomicXCore\/documentation\/AtomicXCore\/CallParams","doc:\/\/AtomicXCore\/documentation\/AtomicXCore\/CallParticipantInfo","doc:\/\/AtomicXCore\/documentation\/AtomicXCore\/CallInfo","doc:\/\/AtomicXCore\/documentation\/AtomicXCore\/CallState","doc:\/\/AtomicXCore\/documentation\/AtomicXCore\/CallEvent"],"anchor":"Related-Documentation"},{"title":"Store","identifiers":["doc:\/\/AtomicXCore\/documentation\/AtomicXCore\/CallState"],"generated":true,"anchor":"Store"}],"schemaVersion":{"patch":0,"major":0,"minor":3},"hierarchy":{"paths":[["doc:\/\/AtomicXCore\/documentation\/AtomicXCore"]]},"abstract":[{"type":"text","text":"Audio\/video call management APIs for initiating, answering, rejecting, hanging up calls, group call management, and call history management."}],"variants":[{"traits":[{"interfaceLanguage":"swift"}],"paths":["\/documentation\/atomicxcore\/callstore"]}],"kind":"symbol","topicSections":[{"title":"Instance Properties","identifiers":["doc:\/\/AtomicXCore\/documentation\/AtomicXCore\/CallStore\/callEventPublisher","doc:\/\/AtomicXCore\/documentation\/AtomicXCore\/CallStore\/state"],"generated":true,"anchor":"Instance-Properties"},{"title":"Instance Methods","identifiers":["doc:\/\/AtomicXCore\/documentation\/AtomicXCore\/CallStore\/accept(completion:)","doc:\/\/AtomicXCore\/documentation\/AtomicXCore\/CallStore\/calls(participantIds:callMediaType:params:completion:)","doc:\/\/AtomicXCore\/documentation\/AtomicXCore\/CallStore\/deleteRecentCalls(callIdList:completion:)","doc:\/\/AtomicXCore\/documentation\/AtomicXCore\/CallStore\/hangup(completion:)","doc:\/\/AtomicXCore\/documentation\/AtomicXCore\/CallStore\/invite(participantIds:params:completion:)","doc:\/\/AtomicXCore\/documentation\/AtomicXCore\/CallStore\/join(callId:completion:)","doc:\/\/AtomicXCore\/documentation\/AtomicXCore\/CallStore\/queryRecentCalls(cursor:count:completion:)","doc:\/\/AtomicXCore\/documentation\/AtomicXCore\/CallStore\/reject(completion:)"],"generated":true,"anchor":"Instance-Methods"},{"title":"Type Properties","identifiers":["doc:\/\/AtomicXCore\/documentation\/AtomicXCore\/CallStore\/shared"],"generated":true,"anchor":"Type-Properties"}],"identifier":{"url":"doc:\/\/AtomicXCore\/documentation\/AtomicXCore\/CallStore","interfaceLanguage":"swift"},"metadata":{"modules":[{"name":"AtomicXCore"}],"externalID":"c:@M@AtomicXCore@objc(cs)CallStore","title":"CallStore","navigatorTitle":[{"text":"CallStore","kind":"identifier"}],"role":"symbol","symbolKind":"class","roleHeading":"Class","fragments":[{"text":"class","kind":"keyword"},{"text":" ","kind":"text"},{"text":"CallStore","kind":"identifier"}]},"references":{"doc://AtomicXCore/documentation/AtomicXCore/CallParticipantStatus":{"type":"topic","role":"symbol","kind":"symbol","navigatorTitle":[{"kind":"identifier","text":"CallParticipantStatus"}],"fragments":[{"kind":"keyword","text":"enum"},{"kind":"text","text":" "},{"kind":"identifier","text":"CallParticipantStatus"}],"title":"CallParticipantStatus","abstract":[{"type":"text","text":"Call participant status, used to identify whether the participant is waiting or has answered."}],"url":"\/documentation\/atomicxcore\/callparticipantstatus","identifier":"doc:\/\/AtomicXCore\/documentation\/AtomicXCore\/CallParticipantStatus"},"doc://AtomicXCore/documentation/AtomicXCore/CallEvent":{"kind":"symbol","abstract":[{"type":"text","text":"Call events, used to receive various event notifications during a call."}],"title":"CallEvent","type":"topic","navigatorTitle":[{"text":"CallEvent","kind":"identifier"}],"identifier":"doc:\/\/AtomicXCore\/documentation\/AtomicXCore\/CallEvent","role":"symbol","fragments":[{"text":"enum","kind":"keyword"},{"text":" ","kind":"text"},{"text":"CallEvent","kind":"identifier"}],"url":"\/documentation\/atomicxcore\/callevent"},"doc://AtomicXCore/objc(cs)NSObject":{"identifier":"doc:\/\/AtomicXCore\/objc(cs)NSObject","type":"unresolvable","title":"ObjectiveC.NSObject"},"doc://AtomicXCore/s28CustomDebugStringConvertibleP":{"type":"unresolvable","identifier":"doc:\/\/AtomicXCore\/s28CustomDebugStringConvertibleP","title":"Swift.CustomDebugStringConvertible"},"doc://AtomicXCore/documentation/AtomicXCore/CallStore":{"title":"CallStore","role":"symbol","type":"topic","abstract":[{"text":"Audio\/video call management APIs for initiating, answering, rejecting, hanging up calls, group call management, and call history management.","type":"text"}],"kind":"symbol","identifier":"doc:\/\/AtomicXCore\/documentation\/AtomicXCore\/CallStore","url":"\/documentation\/atomicxcore\/callstore","fragments":[{"kind":"keyword","text":"class"},{"kind":"text","text":" "},{"kind":"identifier","text":"CallStore"}],"navigatorTitle":[{"kind":"identifier","text":"CallStore"}]},"doc://AtomicXCore/s7CVarArgP":{"identifier":"doc:\/\/AtomicXCore\/s7CVarArgP","type":"unresolvable","title":"Swift.CVarArg"},"doc://AtomicXCore/documentation/AtomicXCore/CallStore/state":{"type":"topic","url":"\/documentation\/atomicxcore\/callstore\/state","fragments":[{"kind":"keyword","text":"let"},{"kind":"text","text":" "},{"kind":"identifier","text":"state"},{"kind":"text","text":": "},{"kind":"typeIdentifier","text":"StatePublisher","preciseIdentifier":"s:11AtomicXCore14StatePublisherC"},{"kind":"text","text":"<"},{"kind":"typeIdentifier","text":"CallState","preciseIdentifier":"s:11AtomicXCore9CallStateV"},{"kind":"text","text":">"}],"abstract":[{"text":"Current call state, including active call, participant list, volume information, network quality, etc.","type":"text"}],"role":"symbol","kind":"symbol","identifier":"doc:\/\/AtomicXCore\/documentation\/AtomicXCore\/CallStore\/state","title":"state"},"doc://AtomicXCore/documentation/AtomicXCore/CallInfo":{"type":"topic","url":"\/documentation\/atomicxcore\/callinfo","title":"CallInfo","abstract":[{"type":"text","text":"Call information, including call ID, room ID, initiator, invitees, media type, call direction, start time, duration, and other complete information."}],"role":"symbol","navigatorTitle":[{"text":"CallInfo","kind":"identifier"}],"kind":"symbol","fragments":[{"text":"struct","kind":"keyword"},{"text":" ","kind":"text"},{"text":"CallInfo","kind":"identifier"}],"identifier":"doc:\/\/AtomicXCore\/documentation\/AtomicXCore\/CallInfo"},"doc://AtomicXCore/documentation/AtomicXCore/CallStore/accept(completion:)":{"url":"\/documentation\/atomicxcore\/callstore\/accept(completion:)","kind":"symbol","title":"accept(completion:)","type":"topic","abstract":[{"type":"text","text":"Answer a call. Call this method to answer the call when receiving an incoming call invitation."}],"fragments":[{"text":"func","kind":"keyword"},{"text":" ","kind":"text"},{"text":"accept","kind":"identifier"},{"text":"(","kind":"text"},{"text":"completion","kind":"externalParam"},{"text":": ","kind":"text"},{"preciseIdentifier":"s:11AtomicXCore17CompletionClosurea","text":"CompletionClosure","kind":"typeIdentifier"},{"text":"?)","kind":"text"}],"role":"symbol","identifier":"doc:\/\/AtomicXCore\/documentation\/AtomicXCore\/CallStore\/accept(completion:)"},"doc://AtomicXCore/documentation/AtomicXCore/CallStore/hangup(completion:)":{"role":"symbol","fragments":[{"text":"func","kind":"keyword"},{"text":" ","kind":"text"},{"text":"hangup","kind":"identifier"},{"text":"(","kind":"text"},{"text":"completion","kind":"externalParam"},{"text":": ","kind":"text"},{"text":"CompletionClosure","preciseIdentifier":"s:11AtomicXCore17CompletionClosurea","kind":"typeIdentifier"},{"text":"?)","kind":"text"}],"title":"hangup(completion:)","type":"topic","abstract":[{"text":"Hang up and end the current ongoing call.","type":"text"}],"identifier":"doc:\/\/AtomicXCore\/documentation\/AtomicXCore\/CallStore\/hangup(completion:)","kind":"symbol","url":"\/documentation\/atomicxcore\/callstore\/hangup(completion:)"},"doc://AtomicXCore/documentation/AtomicXCore/CallParams":{"type":"topic","fragments":[{"text":"struct","kind":"keyword"},{"text":" ","kind":"text"},{"text":"CallParams","kind":"identifier"}],"navigatorTitle":[{"text":"CallParams","kind":"identifier"}],"title":"CallParams","url":"\/documentation\/atomicxcore\/callparams","identifier":"doc:\/\/AtomicXCore\/documentation\/AtomicXCore\/CallParams","kind":"symbol","abstract":[{"text":"Call parameter configuration, used to set room ID, timeout, custom data, and other parameters when initiating an audio\/video call.","type":"text"}],"role":"symbol"},"doc://AtomicXCore/documentation/AtomicXCore/CallMediaType":{"kind":"symbol","identifier":"doc:\/\/AtomicXCore\/documentation\/AtomicXCore\/CallMediaType","url":"\/documentation\/atomicxcore\/callmediatype","role":"symbol","navigatorTitle":[{"text":"CallMediaType","kind":"identifier"}],"title":"CallMediaType","abstract":[{"text":"Call media type, used to specify whether to initiate an audio call or video call.","type":"text"}],"type":"topic","fragments":[{"text":"enum","kind":"keyword"},{"text":" ","kind":"text"},{"text":"CallMediaType","kind":"identifier"}]},"doc://AtomicXCore/documentation/AtomicXCore/CallStore/calls(participantIds:callMediaType:params:completion:)":{"url":"\/documentation\/atomicxcore\/callstore\/calls(participantids:callmediatype:params:completion:)","type":"topic","kind":"symbol","abstract":[{"text":"Create an audio or video call to specified users, supporting both one-on-one and group calls.","type":"text"}],"role":"symbol","fragments":[{"text":"func","kind":"keyword"},{"text":" ","kind":"text"},{"text":"calls","kind":"identifier"},{"text":"(","kind":"text"},{"text":"participantIds","kind":"externalParam"},{"text":": [","kind":"text"},{"text":"String","kind":"typeIdentifier","preciseIdentifier":"s:SS"},{"text":"], ","kind":"text"},{"text":"callMediaType","kind":"externalParam"},{"text":": ","kind":"text"},{"text":"CallMediaType","kind":"typeIdentifier","preciseIdentifier":"s:11AtomicXCore13CallMediaTypeO"},{"text":", ","kind":"text"},{"text":"params","kind":"externalParam"},{"text":": ","kind":"text"},{"text":"CallParams","kind":"typeIdentifier","preciseIdentifier":"s:11AtomicXCore10CallParamsV"},{"text":"?, ","kind":"text"},{"text":"completion","kind":"externalParam"},{"text":": ","kind":"text"},{"text":"CompletionClosure","kind":"typeIdentifier","preciseIdentifier":"s:11AtomicXCore17CompletionClosurea"},{"text":"?)","kind":"text"}],"title":"calls(participantIds:callMediaType:params:completion:)","identifier":"doc:\/\/AtomicXCore\/documentation\/AtomicXCore\/CallStore\/calls(participantIds:callMediaType:params:completion:)"},"doc://AtomicXCore/SQ":{"type":"unresolvable","identifier":"doc:\/\/AtomicXCore\/SQ","title":"Swift.Equatable"},"doc://AtomicXCore/documentation/AtomicXCore/CallStore/deleteRecentCalls(callIdList:completion:)":{"fragments":[{"text":"func","kind":"keyword"},{"text":" ","kind":"text"},{"text":"deleteRecentCalls","kind":"identifier"},{"text":"(","kind":"text"},{"text":"callIdList","kind":"externalParam"},{"text":": [","kind":"text"},{"text":"String","preciseIdentifier":"s:SS","kind":"typeIdentifier"},{"text":"], ","kind":"text"},{"text":"completion","kind":"externalParam"},{"text":": ","kind":"text"},{"text":"CompletionClosure","preciseIdentifier":"s:11AtomicXCore17CompletionClosurea","kind":"typeIdentifier"},{"text":"?)","kind":"text"}],"title":"deleteRecentCalls(callIdList:completion:)","identifier":"doc:\/\/AtomicXCore\/documentation\/AtomicXCore\/CallStore\/deleteRecentCalls(callIdList:completion:)","kind":"symbol","url":"\/documentation\/atomicxcore\/callstore\/deleterecentcalls(callidlist:completion:)","type":"topic","abstract":[{"type":"text","text":"Delete specified call records."}],"role":"symbol"},"doc://AtomicXCore/documentation/AtomicXCore/CallState":{"abstract":[{"type":"text","text":"Call state data, manages the real-time data state of the current call."}],"type":"topic","kind":"symbol","title":"CallState","role":"symbol","identifier":"doc:\/\/AtomicXCore\/documentation\/AtomicXCore\/CallState","fragments":[{"text":"struct","kind":"keyword"},{"text":" ","kind":"text"},{"text":"CallState","kind":"identifier"}],"url":"\/documentation\/atomicxcore\/callstate","navigatorTitle":[{"text":"CallState","kind":"identifier"}]},"doc://AtomicXCore/documentation/AtomicXCore":{"title":"AtomicXCore","kind":"symbol","abstract":[{"text":"AtomicX Core SDK, providing complete features including login, live streaming, calling, messaging, and device management.","type":"text"}],"url":"\/documentation\/atomicxcore","identifier":"doc:\/\/AtomicXCore\/documentation\/AtomicXCore","role":"collection","type":"topic"},"doc://AtomicXCore/documentation/AtomicXCore/CallStore/join(callId:completion:)":{"abstract":[{"text":"Join an ongoing group call using a specific call ID.","type":"text"}],"url":"\/documentation\/atomicxcore\/callstore\/join(callid:completion:)","title":"join(callId:completion:)","fragments":[{"text":"func","kind":"keyword"},{"text":" ","kind":"text"},{"text":"join","kind":"identifier"},{"text":"(","kind":"text"},{"text":"callId","kind":"externalParam"},{"text":": ","kind":"text"},{"text":"String","kind":"typeIdentifier","preciseIdentifier":"s:SS"},{"text":", ","kind":"text"},{"text":"completion","kind":"externalParam"},{"text":": ","kind":"text"},{"text":"CompletionClosure","kind":"typeIdentifier","preciseIdentifier":"s:11AtomicXCore17CompletionClosurea"},{"text":"?)","kind":"text"}],"kind":"symbol","role":"symbol","type":"topic","identifier":"doc:\/\/AtomicXCore\/documentation\/AtomicXCore\/CallStore\/join(callId:completion:)"},"doc://AtomicXCore/documentation/AtomicXCore/CallParticipantInfo":{"type":"topic","role":"symbol","kind":"symbol","navigatorTitle":[{"kind":"identifier","text":"CallParticipantInfo"}],"fragments":[{"kind":"keyword","text":"struct"},{"kind":"text","text":" "},{"kind":"identifier","text":"CallParticipantInfo"}],"abstract":[{"type":"text","text":"Call participant information, including user ID, nickname, avatar, participation status, microphone\/camera on\/off status, etc."}],"identifier":"doc:\/\/AtomicXCore\/documentation\/AtomicXCore\/CallParticipantInfo","title":"CallParticipantInfo","url":"\/documentation\/atomicxcore\/callparticipantinfo"},"doc://AtomicXCore/s23CustomStringConvertibleP":{"identifier":"doc:\/\/AtomicXCore\/s23CustomStringConvertibleP","type":"unresolvable","title":"Swift.CustomStringConvertible"},"doc://AtomicXCore/documentation/AtomicXCore/CallStore/shared":{"fragments":[{"text":"static","kind":"keyword"},{"text":" ","kind":"text"},{"text":"let","kind":"keyword"},{"text":" ","kind":"text"},{"text":"shared","kind":"identifier"},{"text":": ","kind":"text"},{"preciseIdentifier":"c:@M@AtomicXCore@objc(cs)CallStore","text":"CallStore","kind":"typeIdentifier"}],"role":"symbol","kind":"symbol","abstract":[{"type":"text","text":"CallStore singleton instance"}],"identifier":"doc:\/\/AtomicXCore\/documentation\/AtomicXCore\/CallStore\/shared","url":"\/documentation\/atomicxcore\/callstore\/shared","type":"topic","title":"shared"},"doc://AtomicXCore/documentation/AtomicXCore/CallDirection":{"kind":"symbol","role":"symbol","fragments":[{"text":"enum","kind":"keyword"},{"text":" ","kind":"text"},{"text":"CallDirection","kind":"identifier"}],"url":"\/documentation\/atomicxcore\/calldirection","abstract":[{"type":"text","text":"Call direction, used to identify whether the call is incoming, outgoing, or missed."}],"navigatorTitle":[{"text":"CallDirection","kind":"identifier"}],"identifier":"doc:\/\/AtomicXCore\/documentation\/AtomicXCore\/CallDirection","title":"CallDirection","type":"topic"},"doc://AtomicXCore/objc(pl)NSObject":{"type":"unresolvable","identifier":"doc:\/\/AtomicXCore\/objc(pl)NSObject","title":"ObjectiveC.NSObjectProtocol"},"doc://AtomicXCore/documentation/AtomicXCore/CallEndReason":{"title":"CallEndReason","abstract":[{"type":"text","text":"Call end reason, used to identify how the audio\/video call ended (normal hangup, rejection, timeout, etc.)."}],"identifier":"doc:\/\/AtomicXCore\/documentation\/AtomicXCore\/CallEndReason","fragments":[{"text":"enum","kind":"keyword"},{"text":" ","kind":"text"},{"text":"CallEndReason","kind":"identifier"}],"role":"symbol","navigatorTitle":[{"text":"CallEndReason","kind":"identifier"}],"type":"topic","kind":"symbol","url":"\/documentation\/atomicxcore\/callendreason"},"doc://AtomicXCore/documentation/AtomicXCore/CallStore/reject(completion:)":{"identifier":"doc:\/\/AtomicXCore\/documentation\/AtomicXCore\/CallStore\/reject(completion:)","title":"reject(completion:)","type":"topic","url":"\/documentation\/atomicxcore\/callstore\/reject(completion:)","fragments":[{"text":"func","kind":"keyword"},{"text":" ","kind":"text"},{"text":"reject","kind":"identifier"},{"text":"(","kind":"text"},{"text":"completion","kind":"externalParam"},{"text":": ","kind":"text"},{"text":"CompletionClosure","kind":"typeIdentifier","preciseIdentifier":"s:11AtomicXCore17CompletionClosurea"},{"text":"?)","kind":"text"}],"role":"symbol","kind":"symbol","abstract":[{"text":"Reject a call. Call this method to reject the call when receiving an incoming call invitation.","type":"text"}]},"doc://AtomicXCore/SH":{"identifier":"doc:\/\/AtomicXCore\/SH","type":"unresolvable","title":"Swift.Hashable"},"doc://AtomicXCore/documentation/AtomicXCore/CallStore/queryRecentCalls(cursor:count:completion:)":{"role":"symbol","kind":"symbol","type":"topic","title":"queryRecentCalls(cursor:count:completion:)","identifier":"doc:\/\/AtomicXCore\/documentation\/AtomicXCore\/CallStore\/queryRecentCalls(cursor:count:completion:)","fragments":[{"text":"func","kind":"keyword"},{"text":" ","kind":"text"},{"text":"queryRecentCalls","kind":"identifier"},{"text":"(","kind":"text"},{"text":"cursor","kind":"externalParam"},{"text":": ","kind":"text"},{"preciseIdentifier":"s:SS","text":"String","kind":"typeIdentifier"},{"text":", ","kind":"text"},{"text":"count","kind":"externalParam"},{"text":": ","kind":"text"},{"preciseIdentifier":"s:Su","text":"UInt","kind":"typeIdentifier"},{"text":", ","kind":"text"},{"text":"completion","kind":"externalParam"},{"text":": ","kind":"text"},{"preciseIdentifier":"s:11AtomicXCore17CompletionClosurea","text":"CompletionClosure","kind":"typeIdentifier"},{"text":"?)","kind":"text"}],"url":"\/documentation\/atomicxcore\/callstore\/queryrecentcalls(cursor:count:completion:)","abstract":[{"type":"text","text":"Query recent call records with pagination support. Pass an empty string as the initial cursor. For subsequent requests, use the cursor returned in the previous response to fetch the next page. Results are updated asynchronously in "},{"type":"codeVoice","code":"state.recentCalls"},{"type":"text","text":"."}]},"doc://AtomicXCore/documentation/AtomicXCore/CallStore/invite(participantIds:params:completion:)":{"fragments":[{"text":"func","kind":"keyword"},{"text":" ","kind":"text"},{"text":"invite","kind":"identifier"},{"text":"(","kind":"text"},{"text":"participantIds","kind":"externalParam"},{"text":": [","kind":"text"},{"preciseIdentifier":"s:SS","text":"String","kind":"typeIdentifier"},{"text":"], ","kind":"text"},{"text":"params","kind":"externalParam"},{"text":": ","kind":"text"},{"preciseIdentifier":"s:11AtomicXCore10CallParamsV","text":"CallParams","kind":"typeIdentifier"},{"text":"?, ","kind":"text"},{"text":"completion","kind":"externalParam"},{"text":": ","kind":"text"},{"preciseIdentifier":"s:11AtomicXCore17CompletionClosurea","text":"CompletionClosure","kind":"typeIdentifier"},{"text":"?)","kind":"text"}],"role":"symbol","abstract":[{"type":"text","text":"Invite other users to join during an ongoing call."}],"title":"invite(participantIds:params:completion:)","url":"\/documentation\/atomicxcore\/callstore\/invite(participantids:params:completion:)","kind":"symbol","type":"topic","identifier":"doc:\/\/AtomicXCore\/documentation\/AtomicXCore\/CallStore\/invite(participantIds:params:completion:)"},"doc://AtomicXCore/documentation/AtomicXCore/CallStore/callEventPublisher":{"role":"symbol","fragments":[{"text":"let","kind":"keyword"},{"text":" ","kind":"text"},{"text":"callEventPublisher","kind":"identifier"},{"text":": ","kind":"text"},{"text":"PassthroughSubject","kind":"typeIdentifier","preciseIdentifier":"s:7Combine18PassthroughSubjectC"},{"text":"<","kind":"text"},{"text":"CallEvent","kind":"typeIdentifier","preciseIdentifier":"s:11AtomicXCore9CallEventO"},{"text":", ","kind":"text"},{"text":"Never","kind":"typeIdentifier","preciseIdentifier":"s:s5NeverO"},{"text":">","kind":"text"}],"identifier":"doc:\/\/AtomicXCore\/documentation\/AtomicXCore\/CallStore\/callEventPublisher","title":"callEventPublisher","kind":"symbol","abstract":[{"type":"text","text":"Call event publisher, used to subscribe to call events"}],"type":"topic","url":"\/documentation\/atomicxcore\/callstore\/calleventpublisher"}}}